quantrocket_trading_calendars/__init__.py
quantrocket_trading_calendars/_version.py
quantrocket_trading_calendars/calendar_utils.py
quantrocket_trading_calendars/exchange_calendar_aeb.py
quantrocket_trading_calendars/exchange_calendar_asx.py
quantrocket_trading_calendars/exchange_calendar_bm.py
quantrocket_trading_calendars/exchange_calendar_bux.py
quantrocket_trading_calendars/exchange_calendar_bvl.py
quantrocket_trading_calendars/exchange_calendar_bvme.py
quantrocket_trading_calendars/exchange_calendar_cboe.py
quantrocket_trading_calendars/exchange_calendar_ebs.py
quantrocket_trading_calendars/exchange_calendar_enextbe.py
quantrocket_trading_calendars/exchange_calendar_fwb.py
quantrocket_trading_calendars/exchange_calendar_globex.py
quantrocket_trading_calendars/exchange_calendar_iceus.py
quantrocket_trading_calendars/exchange_calendar_kse.py
quantrocket_trading_calendars/exchange_calendar_lse.py
quantrocket_trading_calendars/exchange_calendar_mexi.py
quantrocket_trading_calendars/exchange_calendar_moex.py
quantrocket_trading_calendars/exchange_calendar_nyse.py
quantrocket_trading_calendars/exchange_calendar_ose.py
quantrocket_trading_calendars/exchange_calendar_sbf.py
quantrocket_trading_calendars/exchange_calendar_sehk.py
quantrocket_trading_calendars/exchange_calendar_sehkntl.py
quantrocket_trading_calendars/exchange_calendar_sfb.py
quantrocket_trading_calendars/exchange_calendar_sgx.py
quantrocket_trading_calendars/exchange_calendar_tse.py
quantrocket_trading_calendars/exchange_calendar_tsej.py
quantrocket_trading_calendars/exchange_calendar_vse.py
quantrocket_trading_calendars/exchange_calendar_wse.py
quantrocket_trading_calendars/status.py
quantrocket_trading_calendars-2.0.4.dist-info/LICENSE
quantrocket_trading_calendars-2.0.4.dist-info/METADATA
quantrocket_trading_calendars-2.0.4.dist-info/WHEEL
quantrocket_trading_calendars-2.0.4.dist-info/entry_points.txt
quantrocket_trading_calendars-2.0.4.dist-info/top_level.txt
quantrocket_trading_calendars-2.0.4.dist-info/RECORD
